python_project_manager/__init__.py
python_project_manager/cli_commands.py
python_project_manager/config.py
python_project_manager/dev_only.py
python_project_manager/run_command.py
python_project_manager/venv_helper.py
python_project_manager/builtin_setups/builtin_exe.py
python_project_manager/builtin_setups/builtin_package.py
python_project_manager/ppm_commands/ppm_init.py
python_project_manager/ppm_commands/ppm_install.py
python_project_manager/ppm_commands/ppm_list.py
python_project_manager/ppm_commands/ppm_run.py
python_project_manager/ppm_commands/ppm_venv.py
python_project_manager/ppm_commands/ppm_version.py
python_project_manager-3.0.4.dist-info/LICENSE.txt
python_project_manager-3.0.4.dist-info/METADATA
python_project_manager-3.0.4.dist-info/WHEEL
python_project_manager-3.0.4.dist-info/entry_points.txt
python_project_manager-3.0.4.dist-info/top_level.txt
python_project_manager-3.0.4.dist-info/RECORD
