Metadata-Version: 2.2
Name: python-project-manager
Version: 3.0.4
Summary: A Python package.
License-File: LICENSE.txt
Requires-Dist: python-dotenv~=1.0.1
Requires-Dist: click~=8.1.7
